qtchecker/__init__.py
qtchecker/qtChecker.py
qtchecker-0.4.0.dist-info/METADATA
qtchecker-0.4.0.dist-info/WHEEL
qtchecker-0.4.0.dist-info/top_level.txt
qtchecker-0.4.0.dist-info/RECORD
