Metadata-Version: 2.1
Name: qtchecker
Version: 0.4.0
Summary: Live image viewer application for photon science detectors.
Home-page: https://github.com/jkotan/qtchecker
Author: J.Kotanski
Author-email: jan.kotanski@desy.de
License: GPLv2
Keywords: pyqt gui test checker helper
Platform: UNKNOWN
Classifier: Development Status :: 5 - Production/Stable
Classifier: Intended Audience :: Science/Research
Classifier: Topic :: Scientific/Engineering :: Physics
Classifier: Topic :: Software Development :: Libraries :: Python Modules
Classifier: License :: OSI Approved :: GNU General Public License v2 (GPLv2)
Classifier: Programming Language :: Python :: 2.7
Classifier: Programming Language :: Python :: 3
Classifier: Programming Language :: Python :: 3.4
Classifier: Programming Language :: Python :: 3.5
Classifier: Programming Language :: Python :: 3.6
Classifier: Programming Language :: Python :: 3.7
